entweet/__init__.py
entweet/entweet.py
entweet/Inconsolata-Regular.ttf
entweet-2.0.0.dist-info/DESCRIPTION.rst
entweet-2.0.0.dist-info/entry_points.txt
entweet-2.0.0.dist-info/METADATA
entweet-2.0.0.dist-info/metadata.json
entweet-2.0.0.dist-info/RECORD
entweet-2.0.0.dist-info/top_level.txt
entweet-2.0.0.dist-info/WHEEL
