Metadata-Version: 2.0
Name: entweet
Version: 2.0.0
Summary: Security and verification for Twitter
Home-page: http://lukasa.co.uk/
Author: David Gouldin and Cory Benfield
Author-email: cory@lukasa.co.uk
License: MIT
Platform: UNKNOWN
Classifier: Development Status :: 5 - Production/Stable
Classifier: Intended Audience :: Developers
Classifier: Natural Language :: English
Classifier: Programming Language :: Python
Classifier: Programming Language :: Python :: 2.7
Classifier: Programming Language :: Python :: 3.4
Requires-Dist: Click (~=4.0)
Requires-Dist: Pillow (~=2.8.1)
Requires-Dist: python-gnupg (~=0.3.7)
Requires-Dist: requests-oauthlib (~=0.5.0)
